[{"id":1,"username":"goku","password":"$2b$10$OYbAqOQ6iCiR8oQnpJ7TauX9T6xar.GTTWh0i3qH7UWPSZO5pADta","favs":["1","2",":[object Object]",":Q2vZe1exJJp53jeB73",":SSElRcgyTKAb6",":5n2yeqeDmp2PUyRzlz",":ThFo4QEPeaDVIqLX1g",":5eF84OQYjzdE4ztzpg",":eEjVeFJ9p8gyt0m3Sa",":77aiB1Co76eb9zQBYG","LkwN0t6mGnyzNG3u16","7d0Rsx5bwTbQawK0F8","5eF84OQYjzdE4ztzpg","eEjVeFJ9p8gyt0m3Sa","Tg6sGQJpMS6KMcgjJ3","3ohs7P4IaShiSGvxaE","cnES3AuULUESEyZeKt","w5oeLgw3nKVlyS8rV3","77aiB1Co76eb9zQBYG","CczfnZNxVF9eFDsQ18","U6jH5wAMuAk8U36IYX","7Y0BqmLd2J6ZUeFvI7","j0vnjUEQefNGFaWcLp","gd09Y2Ptu7gsiPVUrv","rnzdOqDvqiFnitaSE1","xUPGcEliCc7bETyfO8","yrRnJXCRgBrdS","r4BmI9xUaDuKJQdd3l","ZOwljDSMNr1rV76DMc","Mx8elxpYeWezisxxwr","Q2i2JJBiW2GpW","cnYo9a9IYylHph7QPC","SIuI7syOPvm1HAd5GF","dWqYBG4PQI9SAuyzDt","14vMxlap9GEaCA","3ohjUUK1x83dobHbEc","xUNd9W6YEPz4W2hE6k","3fD1QmD1w0RVV74psX","c0QST1A56bPxC8ZoiN","bLy8cwoobMGx1uDHkO","GRSnxyhJnPsaQy9YLn","7vP6xnkkOrlGW4TmRR","cb9aF9tDyiRkYbz3BX","kaBwr6sseZ7WkarkqI","6o9jOWQ8ZL19rnhiqy","MkAqCLyL6kJuE","hR0LDEFmKNp2ClAopQ"]},{"id":2,"username":"goku1","password":"$2b$10$Yur9F5eUJHmuMw7AlQVmweLFN2c1Sbu5lC1NAJROz6lD1PAZPGmsS","favs":[]},{"id":3,"username":"assasasasas","password":"$2b$10$JsIzbI5jscl43qBaewepfu/GZC13UpQ2tG0v8tHrJyRXx1uvHdAWa","favs":[]},{"id":4,"username":"goku5","password":"$2b$10$/jbABbi5Tbk.9XavN58IiOc8Jp2XelMpAfSQDAZ7gz0pk6nHbyb.6","favs":[]},{"id":5,"username":"goku7","password":"$2b$10$JLo4kzDxlXyyPEYOqWAIXerCWY8FuF7PdNa0IPauJC.7qVFGMmk/K","favs":[]},{"id":6,"username":"adriano","password":"$2b$10$.WghqpNHcLM8M.QK.EU/keDvGFc1JzMxozO1GsvvzBZFxxNdmmZ5O","favs":[["12112"],"12112"]},{"id":7,"username":"mariano","password":"$2b$10$bB/pm11Z3l2p2Mkm21sz3.07D965fsAJjubSpALXqOl9QK5JBXume","favs":[]},{"id":8,"username":"coco","password":"$2b$10$3WZ2zmYqhSFiMs2wr4D1QuTtpJ5EmvJyi8A0AdywAg9xrZdN9i2AS","favs":[]},{"id":9,"username":"coconut","password":"$2b$10$ZDCqdauFIRZ4Fa2eF6pBHe3tYpraqDxFLCYb/8sYMRK/vv6ieyGaa","favs":[]},{"id":10,"username":"test1","password":"$2b$10$TSodb6usWfUnN1p/xreNJuu1HF9jSh1t9Q3fJcuR41QdoN3KdMiu.","favs":[]},{"id":11,"username":"kakaroto","password":"$2b$10$OG/3E.HSrmr04QVNMoMJAOvIhXyUttq.VS8Pnb3EKAuhrMP2dMxCO","favs":["dWqYBG4PQI9SAuyzDt","xUNd9W6YEPz4W2hE6k","3ohjVaOEKioOLlvLOM"]},{"id":12,"username":"nueva","password":"$2b$10$l6BfBn.j2UIFOkGuzhob/OfVWNU.X4raB.6Qp9Tqkjh4ulnE67Nva","favs":[]},{"id":13,"username":"marrano","password":"$2b$10$hdJdh6M6t8XT1pM8mPOyF.diDKKtNIpIIjUnEb8qZrHCFGIaZznfC","favs":[]},{"id":14,"username":"maarrano2","password":"$2b$10$Ue2gYNRyG3TMoPk0pcfWYOvk/CiPytJDbDpA2jNQWr5mApCk1uOgy","favs":[]},{"id":15,"username":"marrano5","password":"$2b$10$HDJJibgkRTm8Ds9SC//2lOkGRoB.TTyRYV8Gfb1SUC7yzaviNUhy6","favs":[]},{"id":16,"username":"coconut1","password":"$2b$10$Bb8EGuy5BzPzyXVLZR9GQOOgTDZl0bEczrvwNrpXR1SGhhbjEeY/i","favs":[]}]